dev_tools_supporter/__init__.py
dev_tools_supporter/methods.py
dev_tools_supporter-1.2.0.dist-info/LICENSE.txt
dev_tools_supporter-1.2.0.dist-info/METADATA
dev_tools_supporter-1.2.0.dist-info/WHEEL
dev_tools_supporter-1.2.0.dist-info/top_level.txt
dev_tools_supporter-1.2.0.dist-info/RECORD
