Metadata-Version: 2.1
Name: dev_tools_supporter
Version: 1.2.0
Summary: Methods for supportively coding MMO tools
Home-page: https://github.com/2uanDM/dev_tools-supporter
Download-URL: https://github.com/2uanDM/dev_tools-supporter/archive/refs/tags/v.1.1.0.tar.gz
Author: 2uanDM
Author-email: hokage321xxx@gmail.com
License: MIT
Keywords: SOME,MEANINGFULL,KEYWORDS
Classifier: Development Status :: 3 - Alpha
Classifier: Intended Audience :: Developers
Classifier: Topic :: Software Development :: Build Tools
Classifier: License :: OSI Approved :: MIT License
Classifier: Programming Language :: Python :: 3.6
Classifier: Programming Language :: Python :: 3.7
Classifier: Programming Language :: Python :: 3.8
Classifier: Programming Language :: Python :: 3.9
Classifier: Programming Language :: Python :: 3.10
Classifier: Programming Language :: Python :: 3.11
License-File: LICENSE.txt
